Metadata-Version: 2.1
Name: phonetizer-fr-dan
Version: 0.1.0
Summary: Translates French words to phonetics. Checks phonetization.
Home-page: https://github.com/biggoron/phonetizer
Author: Dan Ringwald
Author-email: dan.ringwald12@gmail.com
License: UNKNOWN
Download-URL: https://github.com/biggoron/phonetizer/archive/0.0.4.tar.gz
Platform: UNKNOWN
Classifier: Programming Language :: Python :: 3
Classifier: License :: OSI Approved :: MIT License
Classifier: Operating System :: OS Independent
Requires-Python: >=3.6
